admin_keyboard_shortcuts
