Metadata-Version: 1.0
Name: django-admin-keyboard-shortcuts
Version: 0.1.5
Summary: Keyboard Shortcuts for your Admin Backend
